odoo/addons/account_check_payee/README.rst
odoo/addons/account_check_payee/__init__.py
odoo/addons/account_check_payee/__manifest__.py
odoo/addons/account_check_payee/hooks.py
odoo/addons/account_check_payee/i18n/account_check_payee.pot
odoo/addons/account_check_payee/models/__init__.py
odoo/addons/account_check_payee/models/account_payment.py
odoo/addons/account_check_payee/readme/CONTRIBUTORS.rst
odoo/addons/account_check_payee/readme/DESCRIPTION.rst
odoo/addons/account_check_payee/readme/USAGE.rst
odoo/addons/account_check_payee/static/description/icon.png
odoo/addons/account_check_payee/static/description/index.html
odoo/addons/account_check_payee/views/account_payment_views.xml
odoo/addons/account_check_payee/wizard/__init__.py
odoo/addons/account_check_payee/wizard/account_payment_register.py
odoo/addons/account_check_payee/wizard/account_payment_register_views.xml
odoo_addon_account_check_payee-15.0.1.0.0.2.dist-info/METADATA
odoo_addon_account_check_payee-15.0.1.0.0.2.dist-info/WHEEL
odoo_addon_account_check_payee-15.0.1.0.0.2.dist-info/top_level.txt
odoo_addon_account_check_payee-15.0.1.0.0.2.dist-info/RECORD
